LICENSE
README.md
setup.py
Master_SQLite3/__init__.py
Master_SQLite3/master_sqlite.py
master_sqlite3.egg-info/PKG-INFO
master_sqlite3.egg-info/SOURCES.txt
master_sqlite3.egg-info/dependency_links.txt
master_sqlite3.egg-info/top_level.txt