Metadata-Version: 2.1
Name: master-sqlite3
Version: 0.0.1
Summary: The Master SQLite3 library is a powerful and easy-to-use tool that significantly simplifies interaction with SQLite databases in Python.
Author: Ryan Souza Anselmo
Author-email: ryansouza.cwb@gmail.com
License: MIT License
Keywords: master sqlite3
License-File: LICENSE
